coolmongo.py
coolmongo-2.0.1.dist-info/LICENSE
coolmongo-2.0.1.dist-info/WHEEL
coolmongo-2.0.1.dist-info/METADATA
coolmongo-2.0.1.dist-info/RECORD
