Metadata-Version: 2.1
Name: coolmongo
Version: 2.0.1
Summary: 一个非常优雅的 MongoDB ORM
Keywords: mongodb,pymongo,motor,orm,coolmongo
Author-email: 江南雨上 <lcctoor@outlook.com>
Classifier: License :: OSI Approved :: Apache Software License
Requires-Dist: arts>=2024.2.25
Project-URL: HomePage, https://github.com/lcctoor/arts/tree/main/arts/coolmongo
